text_file_reads_write/文本文件批量读取器.py
text_file_reads_write-0.1.0.dist-info/LICENSE
text_file_reads_write-0.1.0.dist-info/METADATA
text_file_reads_write-0.1.0.dist-info/WHEEL
text_file_reads_write-0.1.0.dist-info/RECORD
